helper_methods/__init__.py
helper_methods/helper/__init__.py
helper_methods/helper/_base.py
helper_methods/helper/jwt_helper.py
helper_methods/helper/request_helper.py
python_test_helper-0.0.2.dist-info/METADATA
python_test_helper-0.0.2.dist-info/WHEEL
python_test_helper-0.0.2.dist-info/top_level.txt
python_test_helper-0.0.2.dist-info/RECORD
