Metadata-Version: 2.1
Name: python-test-helper
Version: 0.0.2
Summary: Simple Methods to help you in your tests
Home-page: https://github.com/delrey1/python-test-helper
Keywords: python
Classifier: Development Status :: 4 - Beta
Classifier: Intended Audience :: Developers
Classifier: Topic :: Software Development :: Libraries
Classifier: Topic :: Software Development :: Libraries :: Python Modules
Classifier: Programming Language :: Python :: 3.7
Classifier: Programming Language :: Python :: 3.8
Classifier: Programming Language :: Python :: 3.9
Classifier: Programming Language :: Python :: 3.10
Classifier: Programming Language :: Python :: 3.11
Requires-Python: >=3.7
Requires-Dist: setuptools (>=21.0.0)
Requires-Dist: requests (>=2.28.2)
Requires-Dist: pydantic
Requires-Dist: pyJWT
